{"type":"FeatureCollection","features":[{"type":"Feature","id":"feedback.15","geometry":{"type":"Point","coordinates":[16.345596313476562,48.21129045708592]},"geometry_name":"geom","properties":{"f_name":"test","f_mail":"test@tes.at","f_anrede":"Herr","f_msg":"los","f_geoweb":0,"f_datum":"12-11-2013","bbox":[16.345596313476562,48.21129045708592,16.345596313476562,48.21129045708592]}},{"type":"Feature","id":"feedback.16","geometry":{"type":"Point","coordinates":[16.345596313476562,48.21129045708592]},"geometry_name":"geom","properties":{"f_name":"test2","f_mail":"test@tes.at","f_anrede":"Herr","f_msg":"los22","f_geoweb":0,"f_datum":"12-11-2013","bbox":[16.345596313476562,48.21129045708592,16.345596313476562,48.21129045708592]}},{"type":"Feature","id":"feedback.17","geometry":{"type":"Point","coordinates":[16.357612609863278,48.192412189186236]},"geometry_name":"geom","properties":{"f_name":"","f_mail":"","f_anrede":" ","f_msg":"testtttt","f_geoweb":0,"f_datum":"12-11-2013","bbox":[16.357612609863278,48.192412189186236,16.357612609863278,48.192412189186236]}},{"type":"Feature","id":"feedback.18","geometry":{"type":"Point","coordinates":[48.192412189186236,16.357612609863278]},"geometry_name":"geom","properties":{"f_name":"ss223","f_mail":"","f_anrede":" ","f_msg":"testtttt","f_geoweb":0,"f_datum":"12-11-2013","bbox":[48.192412189186236,16.357612609863278,48.192412189186236,16.357612609863278]}}],"crs":{"type":"EPSG","properties":{"code":"4326"}},"bbox":[16.345596313476562,16.357612609863278,48.192412189186236,48.21129045708592]}
